cnp_build/__init__.py
cnp_build/build_module.py
cnp_build/cli.py
cnp_make/__init__.py
cnp_make/build_module.py
cnp_make/cli.py
cnp_make-0.0.2.dist-info/METADATA
cnp_make-0.0.2.dist-info/WHEEL
cnp_make-0.0.2.dist-info/entry_points.txt
cnp_make-0.0.2.dist-info/top_level.txt
cnp_make-0.0.2.dist-info/RECORD
