Metadata-Version: 2.1
Name: cnp-make
Version: 0.0.2
Summary: Crea la estructura principal para el desarrollo de nuevos modulos
Home-page: https://github.com/linuxivan
Author: Ivan Perez Louzan
Author-email: iperez@coninpe.es
License: GPLv3
Platform: UNKNOWN
Requires-Dist: argparse
